roboworld/__init__.py
roboworld/vector.py
roboworld/visualization.py
roboworld/world.py
roboworld-0.1.7.dist-info/LICENSE
roboworld-0.1.7.dist-info/METADATA
roboworld-0.1.7.dist-info/WHEEL
roboworld-0.1.7.dist-info/top_level.txt
roboworld-0.1.7.dist-info/RECORD
