Metadata-Version: 2.1
Name: roboworld
Version: 0.1.7
Summary: Educational roboter world to learn basic programming concepts.
Home-page: https://github.com/BZoennchen/robo-world
Author: Benedikt Zoennchen
Author-email: benedikt.zoennchen@web.de
Maintainer: BZoennchen
Maintainer-email: benedikt.zoennchen@web.de
Keywords: education,gamification,cellular automaton,roboter,learning,beginners,computational thinking
Requires-Python: >=3.7.0,<4.0.0
License-File: LICENSE
Requires-Dist: matplotlib
Requires-Dist: numpy
